<?xml version="1.0" encoding="UTF-8"?><wsdl:definitions name="InfoDesg_Sync_Out" targetNamespace="urn:desguaseQM:qm:sap" xmlns:p1="urn:desguaseQM:qm:sap" xmlns:wsp="http://schemas.xmlsoap.org/ws/2004/09/policy" xmlns:wsu="http://docs.oasis-open.org/wss/2004/01/oasis-200401-wss-wssecurity-utility-1.0.xsd" xmlns:wsdl="http://schemas.xmlsoap.org/wsdl/"><wsdl:documentation/><wsp:UsingPolicy wsdl:required="true"/><wsp:Policy wsu:Id="OP_InfoDesg_Sync_Out"/><wsdl:types><xsd:schema targetNamespace="urn:desguaseQM:qm:sap" xmlns:xsd="http://www.w3.org/2001/XMLSchema" xmlns="urn:desguaseQM:qm:sap"><xsd:element name="Respuesta" type="Respuesta"/><xsd:element name="Desguace" type="Desguase"/><xsd:complexType name="Items"><xsd:annotation><xsd:appinfo source="http://sap.com/xi/VersionID">f00a02dda32111e5997700000031bb72</xsd:appinfo></xsd:annotation><xsd:sequence><xsd:element name="Cebe" type="xsd:string" minOccurs="0"><xsd:annotation><xsd:appinfo source="http://sap.com/xi/TextID">31de617da32211e5a94000505682b207</xsd:appinfo></xsd:annotation></xsd:element><xsd:element name="Cuenta" type="xsd:string" minOccurs="0"><xsd:annotation><xsd:appinfo source="http://sap.com/xi/TextID">31de617ea32211e5c4f100505682b207</xsd:appinfo></xsd:annotation></xsd:element><xsd:element name="Material" type="xsd:string"><xsd:annotation><xsd:appinfo source="http://sap.com/xi/TextID">9ced1059882911e3bdb400271041413c</xsd:appinfo></xsd:annotation></xsd:element><xsd:element name="ClaseMov" type="xsd:string" minOccurs="0"><xsd:annotation><xsd:appinfo source="http://sap.com/xi/TextID">bcc569fd87c411e3826d00090ffe0001</xsd:appinfo></xsd:annotation></xsd:element><xsd:element name="Cantidad" type="xsd:decimal" minOccurs="0"><xsd:annotation><xsd:appinfo source="http://sap.com/xi/TextID">bcc569fe87c411e3ba1000090ffe0001</xsd:appinfo></xsd:annotation></xsd:element><xsd:element name="Unid" type="xsd:string" minOccurs="0"><xsd:annotation><xsd:appinfo source="http://sap.com/xi/TextID">bcc569ff87c411e3c35f00090ffe0001</xsd:appinfo></xsd:annotation></xsd:element><xsd:element name="Centro" type="xsd:string" minOccurs="0"><xsd:annotation><xsd:appinfo source="http://sap.com/xi/TextID">bcc56a0087c411e3cc3b00090ffe0001</xsd:appinfo></xsd:annotation></xsd:element><xsd:element name="Almacen" type="xsd:string" minOccurs="0"><xsd:annotation><xsd:appinfo source="http://sap.com/xi/TextID">bcc5953487c411e3a5a200090ffe0001</xsd:appinfo></xsd:annotation></xsd:element><xsd:element name="Lote" type="xsd:string" minOccurs="0"><xsd:annotation><xsd:appinfo source="http://sap.com/xi/TextID">4f05f268887211e3be5a00271041413c</xsd:appinfo></xsd:annotation></xsd:element><xsd:element name="MotivoMov" type="xsd:string" minOccurs="0"><xsd:annotation><xsd:appinfo source="http://sap.com/xi/TextID">bcc5953587c411e3a70b00090ffe0001</xsd:appinfo></xsd:annotation></xsd:element><xsd:element name="ValorMatriz" type="xsd:string" minOccurs="0"><xsd:annotation><xsd:appinfo source="http://sap.com/xi/TextID">bcc5953687c411e3c0e300090ffe0001</xsd:appinfo></xsd:annotation></xsd:element><xsd:element name="Centro_coste" type="xsd:string" minOccurs="0"><xsd:annotation><xsd:appinfo source="http://sap.com/xi/TextID">21015ee2a32211e5cc8b00505682b207</xsd:appinfo></xsd:annotation></xsd:element><xsd:element name="TextoPos" type="xsd:string" minOccurs="0"><xsd:annotation><xsd:appinfo source="http://sap.com/xi/TextID">bcc5953787c411e3ca5b00090ffe0001</xsd:appinfo></xsd:annotation></xsd:element></xsd:sequence></xsd:complexType><xsd:complexType name="Desguase"><xsd:annotation><xsd:appinfo source="http://sap.com/xi/VersionID">140ac17ca32211e5c93d00000031bb72</xsd:appinfo></xsd:annotation><xsd:sequence><xsd:element name="Cabecera" type="Cabecera"><xsd:annotation><xsd:appinfo source="http://sap.com/xi/TextID">e18f4a4ca32111e5af7700505682b207</xsd:appinfo></xsd:annotation></xsd:element><xsd:element name="Items" type="Items" minOccurs="0" maxOccurs="unbounded"><xsd:annotation><xsd:appinfo source="http://sap.com/xi/TextID">e18f4a4da32111e5c77600505682b207</xsd:appinfo></xsd:annotation></xsd:element></xsd:sequence></xsd:complexType><xsd:complexType name="Cabecera"><xsd:annotation><xsd:appinfo source="http://sap.com/xi/VersionID">d0e0eec487cb11e3a39b00000031bb72</xsd:appinfo></xsd:annotation><xsd:sequence><xsd:element name="CodTransaccion" type="xsd:string" minOccurs="0"><xsd:annotation><xsd:appinfo source="http://sap.com/xi/TextID">d24181df87cb11e3c0a600090ffe0001</xsd:appinfo></xsd:annotation></xsd:element><xsd:element name="ClaseMov" type="xsd:string" minOccurs="0"><xsd:annotation><xsd:appinfo source="http://sap.com/xi/TextID">d24181e087cb11e3bbc800090ffe0001</xsd:appinfo></xsd:annotation></xsd:element><xsd:element name="FechaCont" type="xsd:date" minOccurs="0"><xsd:annotation><xsd:appinfo source="http://sap.com/xi/TextID">d24181e187cb11e3960e00090ffe0001</xsd:appinfo></xsd:annotation></xsd:element></xsd:sequence></xsd:complexType><xsd:complexType name="Respuesta"><xsd:annotation><xsd:appinfo source="http://sap.com/xi/VersionID">dea3af600ebd11e599db00000031bb72</xsd:appinfo></xsd:annotation><xsd:sequence><xsd:element name="NumDoc" type="xsd:string" minOccurs="0"><xsd:annotation><xsd:appinfo source="http://sap.com/xi/TextID">0649ffdc0ebe11e5832300ffa6fe27ba</xsd:appinfo></xsd:annotation></xsd:element><xsd:element name="Ejercicio" type="xsd:string" minOccurs="0"><xsd:annotation><xsd:appinfo source="http://sap.com/xi/TextID">0649ffdd0ebe11e5a9c500ffa6fe27ba</xsd:appinfo></xsd:annotation></xsd:element><xsd:element name="MsjResp" minOccurs="0" maxOccurs="unbounded"><xsd:annotation><xsd:appinfo source="http://sap.com/xi/TextID">0649ffe00ebe11e5b6fe00ffa6fe27ba</xsd:appinfo></xsd:annotation><xsd:complexType><xsd:sequence><xsd:element name="Type" type="xsd:string" minOccurs="0"><xsd:annotation><xsd:appinfo source="http://sap.com/xi/TextID">0649ffde0ebe11e5927400ffa6fe27ba</xsd:appinfo></xsd:annotation></xsd:element><xsd:element name="Text" type="xsd:string" minOccurs="0"><xsd:annotation><xsd:appinfo source="http://sap.com/xi/TextID">0649ffdf0ebe11e5c9a100ffa6fe27ba</xsd:appinfo></xsd:annotation></xsd:element></xsd:sequence></xsd:complexType></xsd:element></xsd:sequence></xsd:complexType></xsd:schema></wsdl:types><wsdl:message name="Desguace"><wsdl:documentation/><wsdl:part name="Desguace" element="p1:Desguace"/></wsdl:message><wsdl:message name="Respuesta"><wsdl:documentation/><wsdl:part name="Respuesta" element="p1:Respuesta"/></wsdl:message><wsdl:portType name="InfoDesg_Sync_Out"><wsdl:documentation/><wsdl:operation name="InfoDesg_Sync_Out"><wsdl:documentation/><wsp:Policy><wsp:PolicyReference URI="#OP_InfoDesg_Sync_Out"/></wsp:Policy><wsdl:input message="p1:Desguace"/><wsdl:output message="p1:Respuesta"/></wsdl:operation></wsdl:portType><wsdl:binding name="InfoDesg_Sync_OutBinding" type="p1:InfoDesg_Sync_Out"><soap:binding style="document" transport="http://schemas.xmlsoap.org/soap/http" xmlns:soap="http://schemas.xmlsoap.org/wsdl/soap/"/><wsdl:operation name="InfoDesg_Sync_Out"><soap:operation soapAction="http://sap.com/xi/WebService/soap1.1" xmlns:soap="http://schemas.xmlsoap.org/wsdl/soap/"/><wsdl:input><soap:body use="literal" xmlns:soap="http://schemas.xmlsoap.org/wsdl/soap/"/></wsdl:input><wsdl:output><soap:body use="literal" xmlns:soap="http://schemas.xmlsoap.org/wsdl/soap/"/></wsdl:output></wsdl:operation></wsdl:binding><wsdl:service name="InfoDesg_Sync_OutService"><wsdl:port name="HTTP_Port" binding="p1:InfoDesg_Sync_OutBinding"><soap:address location="http://hermeconpidev.hermeco.local:50000/XISOAPAdapter/MessageServlet?senderParty=&amp;senderService=SAP_I_MODELO_BS&amp;receiverParty=&amp;receiverService=&amp;interface=InfoDesg_Sync_Out&amp;interfaceNamespace=urn%3AdesguaseQM%3Aqm%3Asap" xmlns:soap="http://schemas.xmlsoap.org/wsdl/soap/"/></wsdl:port><wsdl:port name="HTTPS_Port" binding="p1:InfoDesg_Sync_OutBinding"><soap:address location="https://hermeconpidev.hermeco.local:50001/XISOAPAdapter/MessageServlet?senderParty=&amp;senderService=SAP_I_MODELO_BS&amp;receiverParty=&amp;receiverService=&amp;interface=InfoDesg_Sync_Out&amp;interfaceNamespace=urn%3AdesguaseQM%3Aqm%3Asap" xmlns:soap="http://schemas.xmlsoap.org/wsdl/soap/"/></wsdl:port></wsdl:service></wsdl:definitions>